{
  "project_info": {
    "project_number": "546468763992",
    "firebase_url": "https://greenhand-7b6c6-default-rtdb.firebaseio.com",
    "project_id": "greenhand-7b6c6",
    "storage_bucket": "greenhand-7b6c6.appspot.com"
  },
  "client": [
    {
      "client_info": {
        "mobilesdk_app_id": "1:546468763992:android:e6b604509f691aaa5ced2d",
        "android_client_info": {
          "package_name": "com.example.newgreenhands0615"
        }
      },
      "oauth_client": [
        {
          "client_id": "546468763992-imsfmkpqdqefc2gmnj0mu3b3vrjiusam.apps.googleusercontent.com",
          "client_type": 3
        }
      ],
      "api_key": [
        {
          "current_key": "AIzaSyBEE2gJO5MFeFjfkJDRlhNjHmtnrdXvwOk"
        }
      ],
      "services": {
        "appinvite_service": {
          "other_platform_oauth_client": [
            {
              "client_id": "546468763992-imsfmkpqdqefc2gmnj0mu3b3vrjiusam.apps.googleusercontent.com",
              "client_type": 3
            }
          ]
        }
      }
    }
  ],
  "configuration_version": "1"
}